{
    "class_to_idx": {
        "Apple_Gala": 0,
        "Apple_Golden Delicious": 1,
        "Avocado": 2,
        "Banana": 3,
        "Berry": 4,
        "Burmese Grape": 5,
        "Carambola": 6,
        "Date Palm": 7,
        "Dragon": 8,
        "Elephant Apple": 9,
        "Grape": 10,
        "Green Coconut": 11,
        "Guava": 12,
        "Hog Plum": 13,
        "Kiwi": 14,
        "Lichi": 15,
        "Malta": 16,
        "Mango Golden Queen": 17,
        "Mango_Alphonso": 18,
        "Mango_Amrapali": 19,
        "Mango_Bari": 20,
        "Mango_Himsagar": 21,
        "Olive": 22,
        "Orange": 23,
        "Palm": 24,
        "Persimmon": 25,
        "Pineapple": 26,
        "Pomegranate": 27,
        "Watermelon": 28,
        "White Pear": 29
    },
    "idx_to_class": {
        "0": "Apple_Gala",
        "1": "Apple_Golden Delicious",
        "2": "Avocado",
        "3": "Banana",
        "4": "Berry",
        "5": "Burmese Grape",
        "6": "Carambola",
        "7": "Date Palm",
        "8": "Dragon",
        "9": "Elephant Apple",
        "10": "Grape",
        "11": "Green Coconut",
        "12": "Guava",
        "13": "Hog Plum",
        "14": "Kiwi",
        "15": "Lichi",
        "16": "Malta",
        "17": "Mango Golden Queen",
        "18": "Mango_Alphonso",
        "19": "Mango_Amrapali",
        "20": "Mango_Bari",
        "21": "Mango_Himsagar",
        "22": "Olive",
        "23": "Orange",
        "24": "Palm",
        "25": "Persimmon",
        "26": "Pineapple",
        "27": "Pomegranate",
        "28": "Watermelon",
        "29": "White Pear"
    },
    "class_names": [
        "Apple_Gala",
        "Apple_Golden Delicious",
        "Avocado",
        "Banana",
        "Berry",
        "Burmese Grape",
        "Carambola",
        "Date Palm",
        "Dragon",
        "Elephant Apple",
        "Grape",
        "Green Coconut",
        "Guava",
        "Hog Plum",
        "Kiwi",
        "Lichi",
        "Malta",
        "Mango Golden Queen",
        "Mango_Alphonso",
        "Mango_Amrapali",
        "Mango_Bari",
        "Mango_Himsagar",
        "Olive",
        "Orange",
        "Palm",
        "Persimmon",
        "Pineapple",
        "Pomegranate",
        "Watermelon",
        "White Pear"
    ]
}